{
  "galvanised": {
    "name": "ورق گالوانیزه",
    "prices": {
      "0.48": {"1000": 0, "1250": 0},
      "0.58": {"1000": 183000, "1250": 183000},
      "0.7": {"1000": 180000, "1250": 180000},
      "0.8": {"1000": 178000, "1250": 178000},
      "0.9": {"1000": 178000, "1250": 178000},
      "1": {"1000": 178000, "1250": 178000},
      "1.25": {"1000": 178000, "1250": 178000},
      "1.5": {"1000": 178000, "1250": 178000}
    }
  },
  "oil": {
    "name": "ورق روغنی",
    "prices": {
      "0.5": {"1000": 195000, "1250": 0},
      "0.7": {"1000": 0, "1250": 0},
      "0.8": {"1000": 0, "1250": 0},
      "0.9": {"1000": 0, "1250": 0},
      "1": {"1000": 0, "1250": 183000},
      "1.25": {"1000": 0, "1250": 183000},
      "1.5": {"1000": 96000, "1250": 183000},
      "2": {"1000": 0, "1250": 0}
    }
  },
  "stud_prices": {"10": 39500, "11.5": 35500},
  "ceramic_price": 1800,
  "engineering_values": {
    "forming_cost_per_kg": 3000,
    "service_fee_amount": 1000000,
    "service_fee_threshold_kg": 1000
  }
}